{
  "db_name": "PostgreSQL",
  "query": "\n            insert into dropspot.member (organisation_id, user_id, is_admin)\n            values ($1, $2, $3)\n            returning is_admin\n        ",
  "describe": {
    "columns": [
      {
        "ordinal": 0,
        "name": "is_admin",
        "type_info": "Bool",
        "origin": {
          "Table": {
            "table": "member",
            "name": "is_admin"
          }
        }
      }
    ],
    "parameters": {
      "Left": [
        "Uuid",
        "Uuid",
        "Bool"
      ]
    },
    "nullable": [
      false
    ]
  },
  "hash": "1905496979d0893d5f88d53d54720926586736291496d1e4cdc78fb00fc323c6"
}
