{
  "db_name": "PostgreSQL",
  "query": "\n            update dropspot.users\n            set first_name = $2, last_name = $3, email = $4, is_admin = $5, updated_at = now(), updated_by_id = $6\n            where id = $1\n            returning id\n        ",
  "describe": {
    "columns": [
      {
        "ordinal": 0,
        "name": "id",
        "type_info": "Uuid",
        "origin": {
          "Table": {
            "table": "users",
            "name": "id"
          }
        }
      }
    ],
    "parameters": {
      "Left": [
        "Uuid",
        "Text",
        "Text",
        "Text",
        "Bool",
        "Uuid"
      ]
    },
    "nullable": [
      false
    ]
  },
  "hash": "99e902fb8149a536ef78a63179046c26e9b59212cedf7baa4d6af8371fecb86a"
}
