{
  "db_name": "PostgreSQL",
  "query": "\n            insert into dropspot.file (name, size, storage, created_at, created_by_id, expires_at, max_downloads)\n            values ($1, $2, $3, $4, $5, $6, $7)\n            returning id\n        ",
  "describe": {
    "columns": [
      {
        "ordinal": 0,
        "name": "id",
        "type_info": "Uuid",
        "origin": {
          "Table": {
            "table": "file",
            "name": "id"
          }
        }
      }
    ],
    "parameters": {
      "Left": [
        "Text",
        "Int8",
        {
          "Custom": {
            "name": "storage",
            "kind": {
              "Enum": [
                "local",
                "s3",
                "gcs"
              ]
            }
          }
        },
        "Timestamptz",
        "Uuid",
        "Timestamptz",
        "Int4"
      ]
    },
    "nullable": [
      false
    ]
  },
  "hash": "825fcaab6a6bad58048e2b949ced76244fc19fe0eccd0dc2a00c191bb54d5201"
}
